doctly/__init__.py
doctly/client.py
doctly-0.2.1.dist-info/licenses/LICENSE
doctly-0.2.1.dist-info/METADATA
doctly-0.2.1.dist-info/WHEEL
doctly-0.2.1.dist-info/top_level.txt
doctly-0.2.1.dist-info/RECORD
