Metadata-Version: 2.4
Name: doctly
Version: 0.2.1
Summary: Python client library for the Doctly API
Author-email: Doctly <support@doctly.ai>
Project-URL: Homepage, https://doctly.ai
Project-URL: Bug Tracker, https://github.com/doctly/doctly/issues
Project-URL: Documentation, https://github.com/doctly/doctly#readme
Project-URL: Source, https://github.com/doctly/doctly
Keywords: doctly,api,client,pdf,markdown
Classifier: Programming Language :: Python :: 3
Classifier: License :: OSI Approved :: MIT License
Classifier: Operating System :: OS Independent
Classifier: Intended Audience :: Developers
Classifier: Topic :: Software Development :: Libraries :: Python Modules
Requires-Python: >=3.7
License-File: LICENSE
Requires-Dist: requests
Provides-Extra: dev
Requires-Dist: pytest; extra == "dev"
Requires-Dist: responses; extra == "dev"
Dynamic: license-file
